htdefects/__init__.py
htdefects/data/__init__.py
htdefects/data/elemental_volumes.json
htdefects/mixing/__init__.py
htdefects/mixing/calculation.py
htdefects/mixing/defect.py
htdefects/mixing/parsers.py
htdefects/mixing/serializers.py
htdefects/mixing/supercell.py
htdefects/mixing/utils.py
htdefects/mixing/tests/__init__.py
htdefects/mixing/tests/test_calculation.py
htdefects/mixing/tests/test_defect.py
htdefects/mixing/tests/test_mixing.py
htdefects/mixing/tests/test_mixing_calculation.py
htdefects/mixing/tests/test_parsers.py
htdefects/mixing/tests/test_serializers.py
htdefects/mixing/tests/test_supercell.py
htdefects-0.3.0.dist-info/LICENSE
htdefects-0.3.0.dist-info/METADATA
htdefects-0.3.0.dist-info/WHEEL
htdefects-0.3.0.dist-info/top_level.txt
htdefects-0.3.0.dist-info/RECORD
