Metadata-Version: 2.1
Name: htdefects
Version: 0.3.0
Summary: A Python library for high-throughput defect calculations
Home-page: https://gitlab.com/hegdevinayi/citrine-defects
Author: Vinay Hegde
Author-email: hegdevinayi@gmail.com
License: Apache License 2.0
Keywords: DFT high-throughput defects materials
Platform: UNKNOWN
Classifier: Development Status :: 3 - Alpha
Classifier: Programming Language :: Python :: 2
Requires-Dist: six
Requires-Dist: scipy (<=0.18)
Requires-Dist: numpy (<1.16)
Requires-Dist: pypif
Requires-Dist: dfttopif
Requires-Dist: dftinpgen
Requires-Dist: matplotlib (<3)
Requires-Dist: ase (<=3.16)
